Metadata-Version: 2.1
Name: jhcrawler
Version: 0.0.6
Summary: *&*(&^*&*
Home-page: https://github.com/apammaaaa/jhcrawler
Author: sjh
Author-email: 1607837367@qq.com
Requires-Python: >=3.6
